{
  "notes": [
    {
      "id": 1,
      "note": "Suspect is sus",
      "suspect": "Davey Crockett",
      "date": "5/16/1984"
    },
    {
      "note": "Suspect is sus",
      "suspect": "Davey Crockett",
      "date": "5/16/1984",
      "id": 2
    },
    {
      "note": "Suspect is sus",
      "suspect": "Mary Magdalene",
      "date": "5/16/1984",
      "id": 3
    },
    {
      "note": "Suspect is sus",
      "suspect": "Bary Magdalene",
      "date": "5/16/1984",
      "id": 5
    },
    {
      "date": "2021-01-14",
      "suspect": "Stacy",
      "note": "stacy is sus",
      "id": 6
    },
    {
      "date": "2021-01-11",
      "suspect": "Mom",
      "note": "Mom is veeeery sus",
      "id": 7
    },
    {
      "date": "2020-06-10",
      "suspect": "Carl",
      "note": "Carl ate my sandwich that was in the work fridge. Very sus.",
      "id": 8
    },
    {
      "date": "2020-10-07",
      "suspect": "Luna",
      "note": "Luna was being very sus this morning.",
      "id": 9
    },
    {
      "date": "2020-11-03",
      "suspect": "Cinderella",
      "note": "Left a shoe...very sus",
      "id": 10
    }
  ]
}